COPYING
testbuddy_g5k/__init__.py
testbuddy_g5k/testbuddy_g5k.py
testbuddy_g5k-1.0.7.dist-info/COPYING
testbuddy_g5k-1.0.7.dist-info/METADATA
testbuddy_g5k-1.0.7.dist-info/WHEEL
testbuddy_g5k-1.0.7.dist-info/entry_points.txt
testbuddy_g5k-1.0.7.dist-info/RECORD
