Metadata-Version: 2.1
Name: testbuddy-g5k
Version: 1.0.7
Summary: Testbuddy-g5k provides declarative tests for Grid'5000.
Home-page: https://salsa.debian.org/_-/testbuddy-g5k
License: GPL-3.0-or-later
Author: Nikolaos Chatzikonstantinou
Author-email: nchatz314@gmail.com
Requires-Python: >=3.11,<4.0
Classifier: License :: OSI Approved :: GNU General Public License v3 or later (GPLv3+)
Classifier: Programming Language :: Python :: 3
Classifier: Programming Language :: Python :: 3.11
Classifier: Programming Language :: Python :: 3.12
Requires-Dist: click (>=8.1.7,<9.0.0)
Project-URL: Documentation, https://_-.pages.debian.net/testbuddy-g5k
Project-URL: Repository, https://salsa.debian.org/_-/testbuddy-g5k
